nsfw_goto/__init__.py
nsfw_goto-0.2.0.dist-info/LICENSE
nsfw_goto-0.2.0.dist-info/METADATA
nsfw_goto-0.2.0.dist-info/WHEEL
nsfw_goto-0.2.0.dist-info/RECORD
